{
  "lastUpdated": "2025-05-17T12:20:17.066Z",
  "topGainers": [
    {
      "symbol": "BONK",
      "name": "BONK",
      "address": "",
      "price": 0.00001883,
      "priceChange24h": 0,
      "volume24h": 0,
      "profitabilityScore": 10,
      "timestamp": "2025-05-17T12:20:04.158Z",
      "confidence": 0.5,
      "gainRank": 1,
      "profitRank": 2
    },
    {
      "symbol": "Bonk",
      "name": "Bonk",
      "address": "DezXAZ8z7PnrnRJjz3wXBoRgixCa6xjnB7YaB1pPB263",
      "price": 0.00001876,
      "priceChange24h": -11.68,
      "priceChange1h": 0.14,
      "volume24h": 1223359.05,
      "profitabilityScore": 31,
      "timestamp": "2025-05-17T12:20:04.435Z",
      "confidence": 0.8,
      "gainRank": 2,
      "profitRank": 1
    }
  ],
  "topProfitable": [
    {
      "symbol": "Bonk",
      "name": "Bonk",
      "address": "DezXAZ8z7PnrnRJjz3wXBoRgixCa6xjnB7YaB1pPB263",
      "price": 0.00001876,
      "priceChange24h": -11.68,
      "priceChange1h": 0.14,
      "volume24h": 1223359.05,
      "profitabilityScore": 31,
      "timestamp": "2025-05-17T12:20:04.435Z",
      "confidence": 0.8,
      "gainRank": 2,
      "profitRank": 1
    },
    {
      "symbol": "BONK",
      "name": "BONK",
      "address": "",
      "price": 0.00001883,
      "priceChange24h": 0,
      "volume24h": 0,
      "profitabilityScore": 10,
      "timestamp": "2025-05-17T12:20:04.158Z",
      "confidence": 0.5,
      "gainRank": 1,
      "profitRank": 2
    }
  ],
  "all": {
    "BONK": {
      "symbol": "BONK",
      "name": "BONK",
      "address": "",
      "price": 0.00001883,
      "priceChange24h": 0,
      "volume24h": 0,
      "profitabilityScore": 10,
      "timestamp": "2025-05-17T12:20:04.158Z",
      "confidence": 0.5,
      "gainRank": 1,
      "profitRank": 2
    },
    "Bonk": {
      "symbol": "Bonk",
      "name": "Bonk",
      "address": "DezXAZ8z7PnrnRJjz3wXBoRgixCa6xjnB7YaB1pPB263",
      "price": 0.00001876,
      "priceChange24h": -11.68,
      "priceChange1h": 0.14,
      "volume24h": 1223359.05,
      "profitabilityScore": 31,
      "timestamp": "2025-05-17T12:20:04.435Z",
      "confidence": 0.8,
      "gainRank": 2,
      "profitRank": 1
    }
  }
}