{
  "lastUpdated": "2025-05-17T18:38:54.222Z",
  "topGainers": [
    {
      "symbol": "BONK",
      "name": "BONK",
      "address": "",
      "price": 0.00001859,
      "priceChange24h": 0,
      "volume24h": 0,
      "profitabilityScore": 10,
      "timestamp": "2025-05-17T18:38:44.439Z",
      "confidence": 0.5,
      "gainRank": 1,
      "profitRank": 2
    },
    {
      "symbol": "Bonk",
      "name": "Bonk",
      "address": "DezXAZ8z7PnrnRJjz3wXBoRgixCa6xjnB7YaB1pPB263",
      "price": 0.00001848,
      "priceChange24h": -10.45,
      "priceChange1h": -1.05,
      "volume24h": 770357.24,
      "profitabilityScore": 31,
      "timestamp": "2025-05-17T18:38:44.536Z",
      "confidence": 0.8,
      "gainRank": 2,
      "profitRank": 1
    }
  ],
  "topProfitable": [
    {
      "symbol": "Bonk",
      "name": "Bonk",
      "address": "DezXAZ8z7PnrnRJjz3wXBoRgixCa6xjnB7YaB1pPB263",
      "price": 0.00001848,
      "priceChange24h": -10.45,
      "priceChange1h": -1.05,
      "volume24h": 770357.24,
      "profitabilityScore": 31,
      "timestamp": "2025-05-17T18:38:44.536Z",
      "confidence": 0.8,
      "gainRank": 2,
      "profitRank": 1
    },
    {
      "symbol": "BONK",
      "name": "BONK",
      "address": "",
      "price": 0.00001859,
      "priceChange24h": 0,
      "volume24h": 0,
      "profitabilityScore": 10,
      "timestamp": "2025-05-17T18:38:44.439Z",
      "confidence": 0.5,
      "gainRank": 1,
      "profitRank": 2
    }
  ],
  "all": {
    "BONK": {
      "symbol": "BONK",
      "name": "BONK",
      "address": "",
      "price": 0.00001859,
      "priceChange24h": 0,
      "volume24h": 0,
      "profitabilityScore": 10,
      "timestamp": "2025-05-17T18:38:44.439Z",
      "confidence": 0.5,
      "gainRank": 1,
      "profitRank": 2
    },
    "Bonk": {
      "symbol": "Bonk",
      "name": "Bonk",
      "address": "DezXAZ8z7PnrnRJjz3wXBoRgixCa6xjnB7YaB1pPB263",
      "price": 0.00001848,
      "priceChange24h": -10.45,
      "priceChange1h": -1.05,
      "volume24h": 770357.24,
      "profitabilityScore": 31,
      "timestamp": "2025-05-17T18:38:44.536Z",
      "confidence": 0.8,
      "gainRank": 2,
      "profitRank": 1
    }
  }
}