{
  "octaHopUltimate": {
    "name": "Octa-Hop Ultimate",
    "enabled": true,
    "maxProfitPercentPerTrade": 0.25,
    "maxPositionSizePercent": 98,
    "maxTradesPerDay": 15,
    "slippageTolerance": 0.15,
    "targetedTokens": [
      "SOL",
      "USDC",
      "BONK",
      "JUP",
      "MSOL",
      "WBTC",
      "mSOL",
      "jitoSOL",
      "RAY",
      "ORCA"
    ],
    "priorityLevel": 1,
    "useAdvancedRouting": true,
    "useNeuralOptimization": true,
    "useMempoolScanning": true,
    "useHighFrequencyMode": true,
    "description": "Maximum profit 8-hop arbitrage with advanced neural network optimization"
  },
  "megaStablecoinFlash": {
    "name": "Mega-Stablecoin Flash",
    "enabled": true,
    "maxProfitPercentPerTrade": 0.21,
    "maxPositionSizePercent": 97,
    "maxTradesPerDay": 18,
    "slippageTolerance": 0.08,
    "targetedTokens": [
      "USDC",
      "USDT",
      "USDH",
      "UXD",
      "USDR",
      "DAI",
      "BUSD",
      "PYUSD",
      "USDC.e",
      "USDCet"
    ],
    "priorityLevel": 2,
    "useAdvancedRouting": true,
    "useQuantumOptimization": true,
    "useParallelExecution": true,
    "description": "Maximum profit stablecoin arbitrage with quantum-optimized routing"
  },
  "recursiveFlashMegalodon": {
    "name": "Recursive Flash Megalodon",
    "enabled": true,
    "maxProfitPercentPerTrade": 0.19,
    "maxPositionSizePercent": 96,
    "maxTradesPerDay": 22,
    "slippageTolerance": 0.12,
    "targetedTokens": [
      "SOL",
      "USDC",
      "RAY",
      "MSOL",
      "BONK",
      "JUP",
      "WIF",
      "ORCA",
      "MNGO",
      "PYTH"
    ],
    "priorityLevel": 3,
    "useAdvancedRouting": true,
    "useCompoundingTechnique": true,
    "useSandwichStrategy": true,
    "description": "Maximum profit recursive flash strategy with advanced compounding"
  },
  "quantumHyperFlash": {
    "name": "Quantum Hyper-Flash",
    "enabled": true,
    "maxProfitPercentPerTrade": 0.32,
    "maxPositionSizePercent": 99,
    "maxTradesPerDay": 25,
    "slippageTolerance": 0.05,
    "targetedTokens": [
      "SOL",
      "USDC",
      "BONK",
      "JUP",
      "WIF",
      "MEME",
      "PYTH",
      "MNGO",
      "BERN",
      "STRK"
    ],
    "priorityLevel": 0,
    "useAdvancedRouting": true,
    "useQuantumOptimization": true,
    "useParallelExecution": true,
    "useNeuralPricePrediction": true,
    "useMemoryGraphOptimization": true,
    "useMEVProtection": true,
    "useMaximumYieldMode": true,
    "description": "Ultra-high profit quantum-optimized hyper-flash strategy with neural price prediction"
  },
  "solUsdcHyperArbitrage": {
    "name": "SOL-USDC Hyper-Arbitrage",
    "enabled": true,
    "maxProfitPercentPerTrade": 0.29,
    "maxPositionSizePercent": 97,
    "maxTradesPerDay": 18,
    "slippageTolerance": 0.07,
    "targetedTokens": [
      "SOL",
      "USDC",
      "JUP",
      "MSOL",
      "jitoSOL"
    ],
    "priorityLevel": 1,
    "useAdvancedRouting": true,
    "useCrossExchangeArbitrage": true,
    "useAtomicSwaps": true,
    "description": "SOL-USDC focused hyper-arbitrage with atomic swap execution"
  }
}