{
  "tokens": [
    {
      "address": "EKpQGSJtjMFqKZ9KQanSqYXRcF8fBopzLHYxdM65zcjm",
      "symbol": "$WIF",
      "name": "dogwifhat",
      "price": 1.08,
      "priceChange24h": -3.44,
      "priceChange1h": 1.8,
      "volume24h": 282064.47,
      "liquidity": 206.87,
      "score": 27.451056999999995,
      "sources": {
        "pumpFun": false,
        "dexScreener": true,
        "birdeye": false,
        "gmgn": false,
        "jupiter": false
      },
      "lastUpdated": 1748210603131,
      "liquidityUSD": 15515.25
    },
    {
      "address": "DezXAZ8z7PnrnRJjz3wXBoRgixCa6xjnB7YaB1pPB263",
      "symbol": "Bonk",
      "name": "Bonk",
      "price": 0.00001967,
      "priceChange24h": -7.4,
      "priceChange1h": 0.33,
      "volume24h": 18247.89,
      "liquidity": 293.1886666666667,
      "score": 27.523274,
      "sources": {
        "pumpFun": false,
        "dexScreener": true,
        "birdeye": false,
        "gmgn": false,
        "jupiter": false
      },
      "lastUpdated": 1748210603131,
      "liquidityUSD": 21989.15
    },
    {
      "address": "4k3Dyjzvzp8eMZWUXbBCjEvwSkkk59S5iCNLY3QrkX6R",
      "symbol": "RAY",
      "name": "Raydium",
      "price": 2.94,
      "priceChange24h": -7.76,
      "priceChange1h": -1.3,
      "volume24h": 88874.71,
      "liquidity": 4225.277999999999,
      "score": 37.711639,
      "sources": {
        "pumpFun": false,
        "dexScreener": true,
        "birdeye": false,
        "gmgn": false,
        "jupiter": false
      },
      "lastUpdated": 1748210603131,
      "liquidityUSD": 316895.85
    }
  ],
  "topTokens": [
    {
      "address": "4k3Dyjzvzp8eMZWUXbBCjEvwSkkk59S5iCNLY3QrkX6R",
      "symbol": "RAY",
      "name": "Raydium",
      "price": 2.94,
      "priceChange24h": -7.76,
      "priceChange1h": -1.3,
      "volume24h": 88874.71,
      "liquidity": 4225.277999999999,
      "score": 37.711639,
      "sources": {
        "pumpFun": false,
        "dexScreener": true,
        "birdeye": false,
        "gmgn": false,
        "jupiter": false
      },
      "lastUpdated": 1748210603131,
      "liquidityUSD": 316895.85
    },
    {
      "address": "DezXAZ8z7PnrnRJjz3wXBoRgixCa6xjnB7YaB1pPB263",
      "symbol": "Bonk",
      "name": "Bonk",
      "price": 0.00001967,
      "priceChange24h": -7.4,
      "priceChange1h": 0.33,
      "volume24h": 18247.89,
      "liquidity": 293.1886666666667,
      "score": 27.523274,
      "sources": {
        "pumpFun": false,
        "dexScreener": true,
        "birdeye": false,
        "gmgn": false,
        "jupiter": false
      },
      "lastUpdated": 1748210603131,
      "liquidityUSD": 21989.15
    },
    {
      "address": "EKpQGSJtjMFqKZ9KQanSqYXRcF8fBopzLHYxdM65zcjm",
      "symbol": "$WIF",
      "name": "dogwifhat",
      "price": 1.08,
      "priceChange24h": -3.44,
      "priceChange1h": 1.8,
      "volume24h": 282064.47,
      "liquidity": 206.87,
      "score": 27.451056999999995,
      "sources": {
        "pumpFun": false,
        "dexScreener": true,
        "birdeye": false,
        "gmgn": false,
        "jupiter": false
      },
      "lastUpdated": 1748210603131,
      "liquidityUSD": 15515.25
    }
  ],
  "newTokens": [],
  "trendingTokens": [
    {
      "address": "EKpQGSJtjMFqKZ9KQanSqYXRcF8fBopzLHYxdM65zcjm",
      "symbol": "$WIF",
      "name": "dogwifhat",
      "price": 1.08,
      "priceChange24h": -3.44,
      "priceChange1h": 1.8,
      "volume24h": 282064.47,
      "liquidity": 206.87,
      "score": 27.451056999999995,
      "sources": {
        "pumpFun": false,
        "dexScreener": true,
        "birdeye": false,
        "gmgn": false,
        "jupiter": false
      },
      "lastUpdated": 1748210603131,
      "liquidityUSD": 15515.25,
      "trendingScore": 28.206446999999997
    },
    {
      "address": "4k3Dyjzvzp8eMZWUXbBCjEvwSkkk59S5iCNLY3QrkX6R",
      "symbol": "RAY",
      "name": "Raydium",
      "price": 2.94,
      "priceChange24h": -7.76,
      "priceChange1h": -1.3,
      "volume24h": 88874.71,
      "liquidity": 4225.277999999999,
      "score": 37.711639,
      "sources": {
        "pumpFun": false,
        "dexScreener": true,
        "birdeye": false,
        "gmgn": false,
        "jupiter": false
      },
      "lastUpdated": 1748210603131,
      "liquidityUSD": 316895.85,
      "trendingScore": 8.887471000000001
    },
    {
      "address": "DezXAZ8z7PnrnRJjz3wXBoRgixCa6xjnB7YaB1pPB263",
      "symbol": "Bonk",
      "name": "Bonk",
      "price": 0.00001967,
      "priceChange24h": -7.4,
      "priceChange1h": 0.33,
      "volume24h": 18247.89,
      "liquidity": 293.1886666666667,
      "score": 27.523274,
      "sources": {
        "pumpFun": false,
        "dexScreener": true,
        "birdeye": false,
        "gmgn": false,
        "jupiter": false
      },
      "lastUpdated": 1748210603131,
      "liquidityUSD": 21989.15,
      "trendingScore": 1.824789
    }
  ],
  "lastFullUpdate": 0
}