{
  "tokens": [
    {
      "address": "EKpQGSJtjMFqKZ9KQanSqYXRcF8fBopzLHYxdM65zcjm",
      "symbol": "$WIF",
      "name": "dogwifhat",
      "price": 1.1,
      "priceChange24h": -1.04,
      "priceChange1h": 2.48,
      "volume24h": 282387.46,
      "liquidity": 211.97920000000002,
      "score": 28.4586836,
      "sources": {
        "pumpFun": false,
        "dexScreener": true,
        "birdeye": false,
        "gmgn": false,
        "jupiter": false
      },
      "lastUpdated": 1748214409287,
      "liquidityUSD": 15898.440000000002
    },
    {
      "address": "DezXAZ8z7PnrnRJjz3wXBoRgixCa6xjnB7YaB1pPB263",
      "symbol": "Bonk",
      "name": "Bonk",
      "price": 0.00002081,
      "priceChange24h": -1.09,
      "priceChange1h": 5.27,
      "volume24h": 21357.17,
      "liquidity": 308.40186666666665,
      "score": 27.523274,
      "sources": {
        "pumpFun": false,
        "dexScreener": true,
        "birdeye": false,
        "gmgn": false,
        "jupiter": false
      },
      "lastUpdated": 1748214409287,
      "liquidityUSD": 23130.14
    },
    {
      "address": "4k3Dyjzvzp8eMZWUXbBCjEvwSkkk59S5iCNLY3QrkX6R",
      "symbol": "RAY",
      "name": "Raydium",
      "price": 3.12,
      "priceChange24h": -1.91,
      "priceChange1h": 6.11,
      "volume24h": 108835.23,
      "liquidity": 4430.154133333333,
      "score": 37.711639,
      "sources": {
        "pumpFun": false,
        "dexScreener": true,
        "birdeye": false,
        "gmgn": false,
        "jupiter": false
      },
      "lastUpdated": 1748214409287,
      "liquidityUSD": 332261.56
    }
  ],
  "topTokens": [
    {
      "address": "4k3Dyjzvzp8eMZWUXbBCjEvwSkkk59S5iCNLY3QrkX6R",
      "symbol": "RAY",
      "name": "Raydium",
      "price": 3.12,
      "priceChange24h": -1.91,
      "priceChange1h": 6.11,
      "volume24h": 108835.23,
      "liquidity": 4430.154133333333,
      "score": 37.711639,
      "sources": {
        "pumpFun": false,
        "dexScreener": true,
        "birdeye": false,
        "gmgn": false,
        "jupiter": false
      },
      "lastUpdated": 1748214409287,
      "liquidityUSD": 332261.56
    },
    {
      "address": "EKpQGSJtjMFqKZ9KQanSqYXRcF8fBopzLHYxdM65zcjm",
      "symbol": "$WIF",
      "name": "dogwifhat",
      "price": 1.1,
      "priceChange24h": -1.04,
      "priceChange1h": 2.48,
      "volume24h": 282387.46,
      "liquidity": 211.97920000000002,
      "score": 28.4586836,
      "sources": {
        "pumpFun": false,
        "dexScreener": true,
        "birdeye": false,
        "gmgn": false,
        "jupiter": false
      },
      "lastUpdated": 1748214409287,
      "liquidityUSD": 15898.440000000002
    },
    {
      "address": "DezXAZ8z7PnrnRJjz3wXBoRgixCa6xjnB7YaB1pPB263",
      "symbol": "Bonk",
      "name": "Bonk",
      "price": 0.00002081,
      "priceChange24h": -1.09,
      "priceChange1h": 5.27,
      "volume24h": 21357.17,
      "liquidity": 308.40186666666665,
      "score": 27.523274,
      "sources": {
        "pumpFun": false,
        "dexScreener": true,
        "birdeye": false,
        "gmgn": false,
        "jupiter": false
      },
      "lastUpdated": 1748214409287,
      "liquidityUSD": 23130.14
    }
  ],
  "newTokens": [],
  "trendingTokens": [
    {
      "address": "EKpQGSJtjMFqKZ9KQanSqYXRcF8fBopzLHYxdM65zcjm",
      "symbol": "$WIF",
      "name": "dogwifhat",
      "price": 1.1,
      "priceChange24h": -1.04,
      "priceChange1h": 2.48,
      "volume24h": 282387.46,
      "liquidity": 211.97920000000002,
      "score": 28.4586836,
      "sources": {
        "pumpFun": false,
        "dexScreener": true,
        "birdeye": false,
        "gmgn": false,
        "jupiter": false
      },
      "lastUpdated": 1748214409287,
      "liquidityUSD": 15898.440000000002,
      "trendingScore": 28.238746000000003
    },
    {
      "address": "4k3Dyjzvzp8eMZWUXbBCjEvwSkkk59S5iCNLY3QrkX6R",
      "symbol": "RAY",
      "name": "Raydium",
      "price": 3.12,
      "priceChange24h": -1.91,
      "priceChange1h": 6.11,
      "volume24h": 108835.23,
      "liquidity": 4430.154133333333,
      "score": 37.711639,
      "sources": {
        "pumpFun": false,
        "dexScreener": true,
        "birdeye": false,
        "gmgn": false,
        "jupiter": false
      },
      "lastUpdated": 1748214409287,
      "liquidityUSD": 332261.56,
      "trendingScore": 10.883523
    },
    {
      "address": "DezXAZ8z7PnrnRJjz3wXBoRgixCa6xjnB7YaB1pPB263",
      "symbol": "Bonk",
      "name": "Bonk",
      "price": 0.00002081,
      "priceChange24h": -1.09,
      "priceChange1h": 5.27,
      "volume24h": 21357.17,
      "liquidity": 308.40186666666665,
      "score": 27.523274,
      "sources": {
        "pumpFun": false,
        "dexScreener": true,
        "birdeye": false,
        "gmgn": false,
        "jupiter": false
      },
      "lastUpdated": 1748214409287,
      "liquidityUSD": 23130.14,
      "trendingScore": 2.1357169999999996
    }
  ],
  "lastFullUpdate": 0
}