{"SOL":{"price":175.11,"lastUpdated":1748399664633,"source":"coingecko"},"USDC":{"price":0.999778,"lastUpdated":1748399664835,"source":"coingecko"},"USDT":{"price":1,"lastUpdated":1748399665021,"source":"coingecko"},"BTC":{"price":108622,"lastUpdated":1748399665222,"source":"coingecko"},"ORCA":{"price":2.73,"lastUpdated":1748231046357,"source":"coingecko"},"ETH":{"price":2561.53,"lastUpdated":1748231524758,"source":"coingecko"},"JUP":{"price":0.00089953,"lastUpdated":1748231525036,"source":"coingecko"},"BONK":{"price":0.00002043,"lastUpdated":1748399544816,"source":"coingecko"},"RAY":{"price":3.25,"lastUpdated":1748230926276,"source":"coingecko"}}